setup.py
escherauth_go/escher_signer.py
escherauth_go/escher_validator.py
escherauth_go/signer-darwin-10.10-amd64.dylib
escherauth_go/signer-linux-amd64.so
escherauth_go/validator-darwin-10.10-amd64.dylib
escherauth_go/validator-linux-amd64.so
escherauth_go.egg-info/PKG-INFO
escherauth_go.egg-info/SOURCES.txt
escherauth_go.egg-info/dependency_links.txt
escherauth_go.egg-info/not-zip-safe
escherauth_go.egg-info/top_level.txt