Metadata-Version: 1.1
Name: escherauth-go
Version: 0.1.3
Summary: Python wrapper for the Go implementation of the AWS4 compatible Escher HTTP request signing protocol.
Home-page: http://escherauth.io/
Author: Istvan Szenasi
Author-email: szeist@gmail.com
License: MIT
Download-URL: https://github.com/EscherAuth/escher-python
Platform: UNKNOWN
Classifier: Development Status :: 4 - Beta
Classifier: Environment :: Console
Classifier: Programming Language :: Python
Classifier: Intended Audience :: Developers
Classifier: License :: OSI Approved :: MIT License
Classifier: Topic :: Internet :: WWW/HTTP
Classifier: Topic :: Utilities
